Workbook

Sheet Summary
A1: Tony Greenberg site — Next.js migration status
A2: Generated from NEXTJS-MIGRATION-TODO.md on 2026-10-17 by scripts/build-migration-status-report.py — a living document; re-run the script after updating the todo file. Counts are formulas over the Full Detail tab.
A4: Phase | B4: Done | C4: Remaining | D4: Deferred | E4: Total | F4: % Complete
A5: Phase 0 — Bootstrap | B5: =COUNTIFS('Full Detail'!$E$2:$E$361,$A5,'Full Detail'!$C$2:$C$361,"Done") | C5: =COUNTIFS('Full Detail'!$E$2:$E$361,$A5,'Full Detail'!$C$2:$C$361,"Remaining") | D5: =COUNTIFS('Full Detail'!$E$2:$E$361,$A5,'Full Detail'!$C$2:$C$361,"Deferred") | E5: =SUM(B5:D5) | F5: =IF(E5=0,0,B5/E5)
A6: Phase 1 — Sanity Studio & Schema | B6: =COUNTIFS('Full Detail'!$E$2:$E$361,$A6,'Full Detail'!$C$2:$C$361,"Done") | C6: =COUNTIFS('Full Detail'!$E$2:$E$361,$A6,'Full Detail'!$C$2:$C$361,"Remaining") | D6: =COUNTIFS('Full Detail'!$E$2:$E$361,$A6,'Full Detail'!$C$2:$C$361,"Deferred") | E6: =SUM(B6:D6) | F6: =IF(E6=0,0,B6/E6)
A7: Phase 2 — Supabase | B7: =COUNTIFS('Full Detail'!$E$2:$E$361,$A7,'Full Detail'!$C$2:$C$361,"Done") | C7: =COUNTIFS('Full Detail'!$E$2:$E$361,$A7,'Full Detail'!$C$2:$C$361,"Remaining") | D7: =COUNTIFS('Full Detail'!$E$2:$E$361,$A7,'Full Detail'!$C$2:$C$361,"Deferred") | E7: =SUM(B7:D7) | F7: =IF(E7=0,0,B7/E7)
A8: Phase 3 — Shared Layout & Design System | B8: =COUNTIFS('Full Detail'!$E$2:$E$361,$A8,'Full Detail'!$C$2:$C$361,"Done") | C8: =COUNTIFS('Full Detail'!$E$2:$E$361,$A8,'Full Detail'!$C$2:$C$361,"Remaining") | D8: =COUNTIFS('Full Detail'!$E$2:$E$361,$A8,'Full Detail'!$C$2:$C$361,"Deferred") | E8: =SUM(B8:D8) | F8: =IF(E8=0,0,B8/E8)
A9: Phase 4 — Marketing Core Pages (30 routes) | B9: =COUNTIFS('Full Detail'!$E$2:$E$361,$A9,'Full Detail'!$C$2:$C$361,"Done") | C9: =COUNTIFS('Full Detail'!$E$2:$E$361,$A9,'Full Detail'!$C$2:$C$361,"Remaining") | D9: =COUNTIFS('Full Detail'!$E$2:$E$361,$A9,'Full Detail'!$C$2:$C$361,"Deferred") | E9: =SUM(B9:D9) | F9: =IF(E9=0,0,B9/E9)
A10: Phase 5 — Blog Engine (Sanity-backed) | B10: =COUNTIFS('Full Detail'!$E$2:$E$361,$A10,'Full Detail'!$C$2:$C$361,"Done") | C10: =COUNTIFS('Full Detail'!$E$2:$E$361,$A10,'Full Detail'!$C$2:$C$361,"Remaining") | D10: =COUNTIFS('Full Detail'!$E$2:$E$361,$A10,'Full Detail'!$C$2:$C$361,"Deferred") | E10: =SUM(B10:D10) | F10: =IF(E10=0,0,B10/E10)
A11: Phase 6 — BrewSoul (28 routes) | B11: =COUNTIFS('Full Detail'!$E$2:$E$361,$A11,'Full Detail'!$C$2:$C$361,"Done") | C11: =COUNTIFS('Full Detail'!$E$2:$E$361,$A11,'Full Detail'!$C$2:$C$361,"Remaining") | D11: =COUNTIFS('Full Detail'!$E$2:$E$361,$A11,'Full Detail'!$C$2:$C$361,"Deferred") | E11: =SUM(B11:D11) | F11: =IF(E11=0,0,B11/E11)
A12: Phase 7 — PRI & Kava Encyclopedias (19 routes) | B12: =COUNTIFS('Full Detail'!$E$2:$E$361,$A12,'Full Detail'!$C$2:$C$361,"Done") | C12: =COUNTIFS('Full Detail'!$E$2:$E$361,$A12,'Full Detail'!$C$2:$C$361,"Remaining") | D12: =COUNTIFS('Full Detail'!$E$2:$E$361,$A12,'Full Detail'!$C$2:$C$361,"Deferred") | E12: =SUM(B12:D12) | F12: =IF(E12=0,0,B12/E12)
A13: Phase 8 — Attention Theft Manifesto (7 routes) | B13: =COUNTIFS('Full Detail'!$E$2:$E$361,$A13,'Full Detail'!$C$2:$C$361,"Done") | C13: =COUNTIFS('Full Detail'!$E$2:$E$361,$A13,'Full Detail'!$C$2:$C$361,"Remaining") | D13: =COUNTIFS('Full Detail'!$E$2:$E$361,$A13,'Full Detail'!$C$2:$C$361,"Deferred") | E13: =SUM(B13:D13) | F13: =IF(E13=0,0,B13/E13)
A14: Phase 9 — Assessments (33 routes) | B14: =COUNTIFS('Full Detail'!$E$2:$E$361,$A14,'Full Detail'!$C$2:$C$361,"Done") | C14: =COUNTIFS('Full Detail'!$E$2:$E$361,$A14,'Full Detail'!$C$2:$C$361,"Remaining") | D14: =COUNTIFS('Full Detail'!$E$2:$E$361,$A14,'Full Detail'!$C$2:$C$361,"Deferred") | E14: =SUM(B14:D14) | F14: =IF(E14=0,0,B14/E14)
A15: Phase 10 — FauxTony Chatbot — CANCELLED (2026-09-10) | B15: =COUNTIFS('Full Detail'!$E$2:$E$361,$A15,'Full Detail'!$C$2:$C$361,"Done") | C15: =COUNTIFS('Full Detail'!$E$2:$E$361,$A15,'Full Detail'!$C$2:$C$361,"Remaining") | D15: =COUNTIFS('Full Detail'!$E$2:$E$361,$A15,'Full Detail'!$C$2:$C$361,"Deferred") | E15: =SUM(B15:D15) | F15: =IF(E15=0,0,B15/E15)
A16: Phase 11 — Code MCP Server — REBUILT (2026-09-29) | B16: =COUNTIFS('Full Detail'!$E$2:$E$361,$A16,'Full Detail'!$C$2:$C$361,"Done") | C16: =COUNTIFS('Full Detail'!$E$2:$E$361,$A16,'Full Detail'!$C$2:$C$361,"Remaining") | D16: =COUNTIFS('Full Detail'!$E$2:$E$361,$A16,'Full Detail'!$C$2:$C$361,"Deferred") | E16: =SUM(B16:D16) | F16: =IF(E16=0,0,B16/E16)
... A19: Phase 14 — QA & Launch | B19: =COUNTIFS('Full Detail'!$E$2:$E$361,$A19,'Full Detail'!$C$2:$C$361,"Done") | C19: =COUNTIFS('Full Detail'!$E$2:$E$361,$A19,'Full Detail'!$C$2:$C$361,"Remaining") | D19: =COUNTIFS('Full Detail'!$E$2:$E$361,$A19,'Full Detail'!$C$2:$C$361,"Deferred") | E19: =SUM(B19:D19) | F19: =IF(E19=0,0,B19/E19)
A20: TOTAL | B20: =SUM(B5:B19) | C20: =SUM(C5:C19) | D20: =SUM(D5:D19) | E20: =SUM(E5:E19) | F20: =IF(E20=0,0,B20/E20)

Sheet Full Detail
A1: Phase | B1: Route / Item | C1: Status | D1: Notes | E1: Phase name
A2: Phase 0 — Bootstrap
B3: Scaffold Next.js 16 (App Router, TypeScript, Tailwind v4, src/ dir, @/* import alias) at web/ | C3: Done | E3: Phase 0 — Bootstrap
B4: Initialize shadcn/ui (Radix base, Nova preset, CSS variables) | C4: Done | E4: Phase 0 — Bootstrap
B5: Install core UI components (button, card, dialog, sheet, dropdown-menu, accordion, tabs, avatar, tooltip, separator, select, checkbox, radio… | C5: Done | D5: -group, switch, popover, navigation-menu, badge, input, label, skeleton, progress, alert, scroll-area, carousel, aspect-ratio, hover-card, sonner, slider, toggle, toggle-group) | E5: Phase 0 — Bootstrap
B6: Install Sanity (sanity, next-sanity, @sanity/image-url, @sanity/vision, @portabletext/react) | C6: Done | E6: Phase 0 — Bootstrap
B7: Install Supabase (@supabase/supabase-js, @supabase/ssr) | C7: Done | E7: Phase 0 — Bootstrap
B8: Install zod, react-hook-form, @hookform/resolvers, date-fns, next-themes, @anthropic-ai/sdk, reading-time | C8: Done | E8: Phase 0 — Bootstrap
B9: Fix pnpm-workspace.yaml allowBuilds (esbuild, sharp → true) | C9: Done | E9: Phase 0 — Bootstrap
B10: Configure next.config.ts images.remotePatterns (Sanity CDN + legacy Manus/CloudFront hosts, temporary) | C10: Done | E10: Phase 0 — Bootstrap
B11: Read Next.js 16 bundled docs (node_modules/next/dist/docs/) for breaking changes vs | C11: Done | D11: Next 13-15 (proxy.ts vs middleware.ts, Promise params, cache directives, Image config defaults) — confirmed, documented in agent notes | E11: Phase 0 — Bootstrap
B12: pnpm install clean, pnpm dev boots with no errors (verified | C12: Done | D12: Turbopack ready in 375ms, HTTP 200) | E12: Phase 0 — Bootstrap
B13: Add .env.local.example documenting every env var this app needs (Sanity project ID/dataset/token, Supabase URL/anon/service keys, Anthropic API key, site URL) | C13: Done | E13: Phase 0 — Bootstrap
B14: web/README.md rewritten | C14: Done | D14: what this app is, how it relates to the legacy app at the repo root, how to run it, how Sanity/Supabase are wired, Next.js 16 breaking-change notes | E14: Phase 0 — Bootstrap
A15: Phase 1 — Sanity Studio & Schema
B16: Connected to an existing Sanity project already owned by the team ("Tonygreenberg", project ID a3q1cyqs, dataset production) | C16: Done | D16: found via an already-authenticated CLI session rather than creating a new one; recorded in web/.env.local | E16: Phase 1 — Sanity Studio & Schema
B17: Embed Studio at web/src/app/studio/[[...tool]]/page.tsx | C17: Done | E17: Phase 1 — Sanity Studio & Schema
B18: Schema | C18: Done | D18: post (title, slug, subtitle, excerpt, pullQuote, body [portable text], heroImage, author ref, category ref, tags[], publishedAt, readTime, seo) — actual path web/src/sanity/schemas/post.ts | E18: Phase 1 — Sanity Studio & Schema
B19: Schema | C19: Done | D19: author (name, slug, avatar, bio) | E19: Phase 1 — Sanity Studio & Schema
B20: Schema | C20: Done | D20: category (title, slug, description) | E20: Phase 1 — Sanity Studio & Schema
B21: Schema: page (title, slug, body, seo) | C21: Done | D21: for marketing pages that need CMS-editable copy | E21: Phase 1 — Sanity Studio & Schema
B22: Schema: seo object (metaTitle, metaDescription, keywords, ogImage, noIndex) | C22: Done | D22: reused across post/page/pageSeo | E22: Phase 1 — Sanity Studio & Schema
B23: Schema: pageSeo (route-keyed SEO override, not in the original plan | C23: Done | D23: added because this site has far more routes than a page document per route would suit; see the schema file for why) | E23: Phase 1 — Sanity Studio & Schema
B24: Schema | C24: Done | D24: siteSettings singleton (site title, tagline, logo, defaultSeo, navigation, footerColumns, footerText, socialLinks) | E24: Phase 1 — Sanity Studio & Schema
B25: Schema: redirect (source, destination, permanent) | C25: Done | D25: backs the Manus→Next.js 301 map (Phase 12) | E25: Phase 1 — Sanity Studio & Schema
B26: Sanity client + typed query helpers | C26: Done | D26: actual path web/src/lib/sanity/client.ts + queries.ts (not web/src/sanity/* as originally sketched here; schemas live in src/sanity/, app-facing read code lives in src/lib/sanity/) | E26: Phase 1 — Sanity Studio & Schema
B27: Sanity image URL builder helper (web/src/lib/sanity/image.ts) wrapping @sanity/image-url, used by next/image everywhere | C27: Done | E27: Phase 1 — Sanity Studio & Schema
B28: Write one-off migration script (web/scripts/migrate-blog-posts.ts, pnpm migrate:blog [--dry-run]) | C28: Done | D28: reads client/src/data/blogData.json (121 posts) → creates Sanity post documents, idempotent by deterministic _id (skips posts that already exist) | E28: Phase 1 — Sanity Studio & Schema
B29: Ran the migration: 121/121 posts created, 0 errors | C29: Done | D29: Author (Tony Greenberg) and 9 categories auto-created. 22 posts got a real hero image uploaded (17 already on RampRate's own CloudFront + 4 rescued live from the legacy /api/img/ proxy + 1 rescued from /manus-storage/ before Manus is decommissioned). 99 posts have no hero image yet — tracked per-post in BLOG-IMAGE-BRIEFS.md with a suggested generation prompt for each; check them off there as real art goes in via Studio | E29: Phase 1 — Sanity Studio & Schema
B30: Spot-check 5-10 migrated posts in Studio (/studio) | C30: Done | D30: verify body formatting (headings/lists/links) came through correctly from the markdown conversion. Done 2026-10-02 on 30 posts, ours vs live: text and links came through (word counts within 2%, same link counts), but the import kept single-line-break lines inside one block (119 blocks in 78 of 121 posts; one 7,932 characters), so posts ran together and lost ~500 short section headings that live shows. Fixed at render time in src/lib/sanity/legacy-body.ts (one paragraph per line; legacy's "short title-like line = section heading" rule for posts created before 2026-10-02, never for a line with a web address), run before autoLinkBody on /blog/[slug]. No Sanity drafts needed. Re-checked: 145 of 162 live headings now match on 30 posts (was ~0 of the plain ones); the rest are live's own quirks (raw #/ Markdown showing on live) or headings already styled in Sanity. | E30: Phase 1 — Sanity Studio & Schema
B31: Real bug found and fixed | C31: Done | D31: markdown-to-portable-text.ts's list-item conversion only ever looked for a "text"-type token inside item.tokens; marked wraps any "loose" list item (one followed by a body paragraph on the next line — e.g. five-cups' "Five Questions Worth Sitting With") in a "paragraph" token instead, so every such item silently converted to an empty Portable Text block (visible live as a bare, contentless numbered list). Fixed the converter to handle both token shapes, then wrote scripts/backfill-list-item-content.ts (idempotent, patches only body) and ran it against all 121 already-migrated posts — 6 posts had at least one empty list item; all 6 fixed in place. | E31: Phase 1 — Sanity Studio & Schema
A32: Phase 2 — Supabase
B33: Supabase project created (2026-10-01): tonygreenberg (free plan, West US), https://zukaqnbknrsmixjvozlj.supabase.co | C33: Done | D33: URL, publishable key (in NEXT_PUBLIC_SUPABASE_ANON_KEY, the name the code reads) and secret key are in .env.local; all three checked against Supabase's API. Not yet in Netlify (its three Supabase settings are still empty). With the keys set, src/proxy.ts is active locally: a production build still serves every page (checked /, /blog, a post, /the-letter, /living-declaration, /america-unbundled, /studio, /login, redirects, 404s). Found: supabase/migrations/0001_init.sql isn't in the repo (the folder is empty), so no tables exist yet, and /login sends a signed-in user to /dashboard/approvals, which was never built (the approval dashboard was replaced by the MCP server). Needs a decision on what Supabase is for before tables or accounts are made. | E33: Phase 2 — Supabase
B34: web/src/lib/supabase/server.ts (SSR client for Server Components/Actions, current getAll/setAll cookie API) and client.ts (browser client) helpers | C34: Done | E34: Phase 2 — Supabase
B35: web/src/lib/supabase/service-role.ts | C35: Done | D35: bypasses RLS, server-only, for chat logging (not in the original plan, but required to satisfy "service-role write only, no public read" below) | E35: Phase 2 — Supabase
B36: web/src/proxy.ts | C36: Done | D36: Supabase's required session-refresh middleware, renamed to proxy.ts per Next.js 16. Ships with a guard: if NEXT_PUBLIC_SUPABASE_URL/_ANON_KEY aren't set yet, it no-ops instead of throwing — without that guard it took the entire site down (every route 500'd) the moment it was added, since it ran on every request. Safe to leave in place; it activates automatically once real credentials land in .env.local | E36: Phase 2 — Supabase
B37: Auth: email/password login for internal approvers | C37: Done | D37: web/src/app/(auth)/login/page.tsx + login-form.tsx + actions.ts (Server Action via useActionState, real spinner on submit per the loader rule in CONTRIBUTING.md, not text). Renders correctly now (verified: HTTP 200, real form) but signing in will fail until the Supabase project above actually exists | E37: Phase 2 — Supabase
B38: SQL migration written (web/supabase/migrations/0001_init.sql) | C38: Done | D38: change_requests table, chat_conversations + chat_messages tables, RLS enabled on all three. Not yet run against a live database — needs the project above first (supabase db push once the CLI is linked, or paste into the SQL editor) | E38: Phase 2 — Supabase
B39: Row-level security policies written in that same migration | C39: Done | D39: authenticated-only read/write on change_requests (noted in-file to scope tighter than "any authenticated user" once more accounts exist); chat tables get RLS enabled with zero policies for anon/authenticated, which is what actually enforces "service-role write only, no public read" (service role bypasses RLS entirely — that's not a policy, it's the point) | E39: Phase 2 — Supabase
B40: Member accounts (2026-10-06, owner chose email + password) | C40: Done | D40: /login, /signup, /forgot-password, /reset-password, /auth/callback (confirm/reset email links; records an invite referral on first confirm). Server actions in src/app/(auth)/actions.ts; Formik + Yup on the 3-field forms; helpers in src/lib/auth.ts (getUser, requireUser, isAdmin via ADMIN_EMAILS), src/lib/supabase/service-role.ts, src/lib/referrals.ts. The old internal-approver login (redirected to a dashboard that was never built) is replaced. Tested on a production build: pages, form checks, wrong-password message, redirects. Not tested: a real sign-up (would create a real account and send a real email). | E40: Phase 2 — Supabase
B41: Fix the Supabase secret key (found 2026-10-09, fixed 2026-10-10) | C41: Done | D41: SUPABASE_SERVICE_ROLE_KEY in .env.local and in Netlify is a damaged copy of the project's secret key (44 characters, the real sb_secret_… key has 41), so every server-side Supabase call fails ("Invalid API key"): comments, reactions, ratings, Ask Tony, highlights, invites, Clock Keeper, post-intervention, friend gate, the /pri-efficacy Live tab. Fix: Supabase dashboard > Project Settings > API Keys > Secret keys > copy the default key, paste it as SUPABASE_SERVICE_ROLE_KEY in .env.local and in Netlify (all scopes), redeploy. (The AI session wasn't allowed to write secrets.) The publishable key (NEXT_PUBLIC_SUPABASE_ANON_KEY) is correct. Fixed 2026-10-10 (owner: "fix all"): the real default secret key (41 chars) read through the Management API with SUPABASE_ACCESS_TOKEN, written to .env.local and to Netlify as a secret (production, deploy previews, branch deploys) without being printed; checked: REST read 200, essays show the copied reactions ("1 reader reacted" on human-operating-system), a quiz finish saves a row. | E41: Phase 2 — Supabase
B42: Set SANITY_WEBHOOK_SECRET (found 2026-10-09, done 2026-10-10) | C42: Done | D42: missing in Netlify and .env.local, so Sanity's publish webhook to /api/revalidate is refused and edits appear only after the 60-second refresh. Create the webhook secret in Sanity (manage > API > Webhooks) and add it to Netlify. 2026-10-10: a random 64-character secret is now in .env.local and in Netlify (secret; production, deploy previews, branch deploys). /api/revalidate checked on a local production build: correctly signed request 200 revalidated, wrong signature 401. Left (Sanity dashboard, the site's Sanity token can't manage webhooks): sanity.io/manage > project a3q1cyqs > API > Webhooks > Create: URL https://tonygreenberg-website.netlify.app/api/revalidate (switch to https://tonygreenberg.com/api/revalidate at cutover), dataset production, trigger on create/update/delete, HTTP method POST, secret = the SANITY_WEBHOOK_SECRET value in .env.local. Done 2026-10-10: the owner created the webhook in Sanity (name tonygreenberg, URL https://tonygreenberg-website.netlify.app/api/revalidate, dataset production, enabled), with the secret from .env.local. At cutover: change its URL to https://tonygreenberg.com/api/revalidate. | E42: Phase 2 — Supabase
B43: Email for the Three Friends Gate (done 2026-10-10) | C43: Done | D43: create a free account at resend.com, verify a sending domain (adds DNS records on tonygreenberg.com, so whoever manages DNS), then set RESEND_API_KEY and EMAIL_FROM (e.g. Only Time Buys Trust <trust@tonygreenberg.com>) in Netlify and .env.local. Until then invites and codes are not sent (logged on the server instead). 2026-10-10: Resend account exists and tonygreenberg.com is verified (also ramprate.com; flow.tonygreenberg.com shows failed, not used here). RESEND_API_KEY is in .env.local (key checked with a read-only domain list) and EMAIL_FROM set to Only Time Buys Trust <trust@tonygreenberg.com> (owner's choice). Test email sent 2026-10-10 (owner asked) to web.master@ramprate.com from Only Time Buys Trust <trust@tonygreenberg.com>: Resend reports delivered. Added to Netlify 2026-10-10 (owner asked; through the CLI with the site's Netlify token): RESEND_API_KEY as a secret in production, deploy previews and branch deploys; EMAIL_FROM in all contexts. The sender is now also the built-in default in src/lib/email.ts (owner: no need for it in .env.local), so EMAIL_FROM is optional. Left: the next deploy picks them up (redeploy or merge). | E43: Phase 2 — Supabase
B44: Old site's visitor data from the Manus database (owner asked, 2026-10-09) | C44: Done | D44: Connection line removed from .env.local 2026-10-10 (owner: "remove the old db"; all data backed up and in Supabase's legacy schema). Done: read-only check of all 56 tables and a full private backup (75,128 rows) to ~/Desktop/tonyg-site-backups/legacy-db-export-2026-10-09/ on the webmaster's Mac (personal data: never commit); most rows are the Manus agent's automated tests (details: docs/ai/project_legacy_database.md); the 198 short share links /s/<code> now redirect (src/lib/content/short-links.ts; 196 land on a page, 2 targets don't exist on live either). Done 2026-10-09 (owner said yes): email subscribers in Kit with no email sent (5 already there, 27 added on the new tag "Legacy site import 2026-10-09", 4 refused by Kit's suppression list); the missing 2026-10-07 Daily Provocation added; supplier forms: table script supabase/migrations/0003_legacy_vendor_intake.sql and scripts/import-legacy-vendor-intake.ts ready (owner: supplier forms to Supabase, everything else stays in the backup). Done 2026-10-09 (owner: "add all data in old db to new supabase"): every legacy table copied into a private legacy schema in Supabase (55 tables, 75,089 rows, counts match; the old app's migration log skipped), row-level security on, not exposed to the site's API, no access for anon/authenticated; the 8 supplier forms also in public.legacy_vendor_intake. Left: the site's Supabase secret key is wrong (see Phase 2); rotate the old database password and remove LEGACY_DATABASE_URL; remove SUPABA | E44: Phase 2 — Supabase
B45: Copy the old essay reactions, ratings and micro-commitment into the live tables (2026-10-10, owner asked) | C45: Done | D45: Mapping done (docs/ai/project_legacy_database.md, "Where the archived data is used"); script supabase/migrations/0004_copy_legacy_engagement.sql copies legacy.post_reactions / blog_ratings / micro_commitments into public.blog_reactions / blog_ratings / blog_commitments, safe to run twice, ends with a row count. Left: run it in Supabase > SQL Editor, then open an essay that had a reaction and check the count shows (needs the Supabase secret key fixed first, item above). Done 2026-10-10: 0004 run through the Management API: 4 reactions, 2 ratings, 1 micro-commitment copied; all 5 essays they belong to exist (200); human-operating-system shows "1 reader reacted" in a browser. | E45: Phase 2 — Supabase
B46: Quiz results and journey progress in Supabase (2026-10-10, owner chose these two of the old site's database features) | C46: Done | D46: Built: tables assessment_results and journey_progress (supabase/migrations/0005_assessments.sql, which also copies the old site's 24 real quiz results; its 1,008 test rows are skipped), server actions src/app/assessments/actions.ts, wired into the shared quiz-finish helpers so every quiz's finish and result is saved, and signed-in members' Journey Tracker progress follows them across devices. Checked: type check, lint, build. Left: run 0005 in Supabase > SQL Editor (after 0004), then finish one quiz on a deploy preview and see the row in the Table Editor (needs the secret key fixed). Done 2026-10-10: 0005 run (tables created, 24 real old results copied: the-mirror 10, dharma-finder 6, consciousness-scale 4, grant-study 2, find-your-therapy 2). Tested in Chromium on a local production build: finishing /find-your-me saved one row with its result ("The Systems Architect"). Found and fixed on the way: the two save calls per finish ran one after another (~2.7 s each), so leaving within ~5 s lost the result text; now merged in the browser into one call (src/lib/assessments/record-finish.ts, 1.5 s window) and the server does one read instead of two (1.5 s). Test rows deleted. Signed-in sync tested 2026-10-10 with a temporary account (created and deleted through the admin API): device A finished /find-your-me, the account got the journey_progress row and its result; a fresh browser (device B) signed in and its Journey list showed find-your-me. | E46: Phase 2 — Supabase
... B48: Database scripts run (2026-10-09, through a Supabase access token the owner added) | C48: Done | D48: 0001, 0002 and 0003, 13 tables, row-level security on, 5 policies; checked through the Management API. (Correction: the project was never paused; this Mac's DNS briefly failed to resolve its address.) Original item: run the database scripts once, in order (supabase/migrations/0001_member_features.sql, then 0002_blog_engagement.sql, then 0003_legacy_vendor_intake.sql for essay comments, reactions, ratings and micro-commitments; 0001: highlights, referral codes/referrals, Clock Keeper responses, post-intervention, friend gate, PRI calibrations, all with row-level security) in Supabase: SQL Editor > New query > paste > Run. Also in Supabase: Authentication > URL Configuration > Site URL https://tonygreenberg.com and Redirect URLs https://tonygreenberg.com/auth/callback, https://*--tonygreenberg-website.netlify.app/auth/callback, http://localhost:3000/auth/callback. Then set NEXT_PUBLIC_SUPABASE_URL, NEXT_PUBLIC_SUPABASE_ANON_KEY, SUPABASE_SERVICE_ROLE_KEY, ADMIN_EMAILS in Netlify. | E48: Phase 2 — Supabase
A49: Phase 3 — Shared Layout & Design System
B50: Root layout (web/src/app/layout.tsx) | C50: Done | D50: fonts (Playfair Display / DM Mono / Source Sans 3 via next/font/google), <TooltipProvider>, theme provider (next-themes, class strategy), global <Toaster /> (sonner), skip-to-content link | E50: Phase 3 — Shared Layout & Design System
B51: Global metadata defaults in root layout (metadataBase, title template, default OG/Twitter card) | C51: Done | E51: Phase 3 — Shared Layout & Design System
B52: Favicon (src/app/icon.tsx) | C52: Done | D52: real brand mark, not the default Next.js icon: a generated 32×32 PNG of the "G" from the header's actual "TonyG" wordmark (Playfair Display, brand-gold), since the full wordmark doesn't read at favicon scale. Deleted the stale default favicon.ico. | E52: Phase 3 — Shared Layout & Design System
B53: Header/nav component (site-header.tsx) | C53: Done | D53: real nav structure ported from legacy Layout.tsx (primary links, "Fix Myself"/"Explore" mega-menus, socials, theme toggle), built with shadcn NavigationMenu. Deliberately not ported: StartHereBanner, ExitIntentTony, TonyAvatarTrigger, NotificationBell, ReadingStreakBadge, WhereNext — separate behavioral/engagement features, not core layout, out of scope for this phase | E53: Phase 3 — Shared Layout & Design System
B54: Mobile nav (shadcn Sheet + Accordion, real nav content, no framer-motion) | C54: Done | E54: Phase 3 — Shared Layout & Design System
B55: Footer component (site-footer.tsx) | C55: Done | D55: real content ported from Layout.tsx's footer JSX (quote, contact, BioChain routing note, socials, CTAs, bio line, legal/copyright). Note: footerData.json turned out to be per-post article-footer data (exercise/related/riddle/CTA), not site footer content — that belongs in Phase 5, not here | E55: Phase 3 — Shared Layout & Design System
B56: Brand design tokens in globals.css (--brand-gold/--brand-gold-light/backgrounds/borders) ported from the real site palette (#8B6914, #D4B96A… | C56: Done | D56: , #0A0A10, #FAFAF7, purple-tinted borders) instead of shadcn's default grayscale theme | E56: Phase 3 — Shared Layout & Design System
B57: Shared typography components | C57: Done | D57: ended up built directly in Phase 5 (portable-text.tsx, drop-cap CSS, pull-quote block) rather than as a separate Phase 3 deliverable, since that's where they're actually consumed | E57: Phase 3 — Shared Layout & Design System
B58: robots.ts (AI crawlers explicitly allowed per the current SEO plan, scraper bots blocked) and sitemap.ts (live from Sanity post slugs alread… | C58: Done | D58: y, extended per-section in later phases) | E58: Phase 3 — Shared Layout & Design System
B59: Error boundary (error.tsx) and not-found.tsx (real legacy 404 copy + countdown-redirect behavior ported from pages/NotFound.tsx) | C59: Done | E59: Phase 3 — Shared Layout & Design System
B60: Loading UI (loading.tsx) using shadcn Skeleton | C60: Done | E60: Phase 3 — Shared Layout & Design System
B61: Icon library decision | C61: Done | D61: lucide-react for all standard UI icons (menu, sun/moon, chevrons); react-icons/fa6 only for the X/LinkedIn brand marks, since lucide-react v1 dropped brand/logo icons entirely | E61: Phase 3 — Shared Layout & Design System
B62: Top-of-page navigation progress bar (nav-progress-bar.tsx) | C62: Done | D62: visible feedback on route transitions, built on the Navigation API (window.navigation) rather than a dependency like nprogress; progressive enhancement, renders nothing where unsupported | E62: Phase 3 — Shared Layout & Design System
B63: Verify header/footer/nav visually in a real browser | C63: Done | D63: Done 2026-09-29 with side-by-side Playwright screenshots against the live tonygreenberg.com at 1280/1536px. The header was rebuilt to match legacy Layout.tsx: full-width translucent cream bar, purple hairline, 0.78rem semi-bold mono nav right-aligned, gold active link, tagline at legacy's breakpoints, and the "Ask Tony ⌘K" pill (legacy TonyDiscovery; it opens site search because the FauxTony chat half was cancelled), plus X/LinkedIn icons and the theme toggle. Also matched from the live site: the Four Doors modal (legacy FourDoorsModal.tsx: image header, Door badge, ochre rule, dark CTA, bottom sheet on mobile), the homepage BrewSoul "Intelligence Engine" band (legacy BrewSoulHero.tsx, background photo rescued into Sanity), and the default theme, now light and not following the OS, same as legacy's ThemeContext. The "New here? 90-second tour" banner (StartHereBanner) is still intentionally not ported. | E63: Phase 3 — Shared Layout & Design System
A64: Phase 4 — Marketing Core Pages (30 routes)
B65: / (homepage) | C65: Done | D65: Blog.tsx. Not the same page as /the-letter — legacy actually routes path="/" to the Blog component, not Home.tsx (Home.tsx is legacy's /the-letter, already ported separately below); this had briefly regressed to a plain paginated post list before this pass corrected it. Real content ported: hero (headline, stats line, essay count/nav line), Four Doors (Read/Diagnose/Engage/Verify — reusing the shared FourDoors component built for /the-letter; its icon-tile fallback path stays in four-doors.tsx for resilience, but all 4 real source photos are now live — see the follow-up pass note below), Editor's Picks (5 real curated posts), GemSpark Strip (a real, small editorial motif — only 3 posts in the whole corpus reference it; hand-ported subtitles since Portable Text has no raw-heading string left to regex the way legacy did), Case File banner, Latest Thinking, Positioning Statement, Core Themes (4 theme cards linking to /?theme=X#essays-archive, read by the archive below), Ecosystem CTA (essay count now live from Sanity instead of legacy's stale hardcoded "ninety-one"), and the full searchable/filterable archive + sidebar (Curated Journeys, Tip Me Off, Follow). Intentionally not ported: the ABIT waitlist email-capture form (posts to a tRPC subscribe mutation — a backend/CRM feature, out of this migration's "no backend features" scope, not a content gap) and legacy's "Most Read"/"Most Provocative" sidebar widgets (both ranked by a reads count that defaulted to a flat placeholder val | E65: Phase 4 — Marketing Core Pages (30 routes)
B66: /the-letter | C66: Done | D66: Home.tsx. Real content/links/data ported (hero, Three Paths, Start Here essays, Four Doors as a shadcn Dialog instead of the legacy custom modal, Featured Essay pulled live from Sanity, How Tony Works, Investment Thesis, Open Questions, What I Build, Most Read, BrewSoul teaser). Deliberately not reproduced: floating-particle animation, glowing-bowl gradients, glitch text, magnetic-hover physics, typewriter intro — decorative flourishes, same judgment call as Phase 3's engagement widgets. Rescued 5 images (hero + 4 door photos) from the still-live legacy /api/img/ proxy into Sanity before porting (scripts/rescue-homepage-images.ts) rather than reference the fragile path. Fixed 2 legacy bugs found while porting: /ramprate and /human-os linked to routes that don't exist (corrected to https://ramprate.com and /humanos); "Most Read"'s 5 items all pointed at the same generic /blog placeholder instead of each post's real slug — corrected using the real migrated post slugs. Verified live: 200 OK, real content, fixed links, real images, no leaked inline styles, lint+typecheck clean. | E66: Phase 4 — Marketing Core Pages (30 routes)
B67: /walk-through | C67: Done | D67: WalkThrough.tsx. Real content ported (7 doors, entity pills w/ real named investments, "Ask me about" lines, cross-links, pull quotes, "The Lesson" callout). Hero reuses the Tony headshot already rescued to Sanity (Phase 12 JSON-LD work) rather than re-fetching. Not ported: AutoLinkedText's automatic entity hyperlinking — that's driven by the site-wide linkMap.ts, a genuine cross-cutting feature affecting many pages, not a one-off for this page; folded into the existing "preserve internal cross-link structure" open item in Phase 5. Verified live: 200 OK, real content, real image, correct next-page link. | E67: Phase 4 — Marketing Core Pages (30 routes)
B68: /the-territory | C68: Done | D68: Territory.tsx. Real content ported (10 heroes/influences with full notes, Operating Philosophy, pull quote, "The Lesson" callout, next-page link). Verified live: 200 OK, real content, correct next-page link. | E68: Phase 4 — Marketing Core Pages (30 routes)
B69: /engine-room | C69: Done | D69: EngineRoom.tsx. Real content ported (6 active ventures, 4 active engagements, pull quote, "The Lesson" callout, next-page link). Verified live: 200 OK, real content, correct next-page link. | E69: Phase 4 — Marketing Core Pages (30 routes)
B70: /under-nda | C70: Done | D70: UnderNDA.tsx. Real content ported (Corridor overview, pull quote, "What We're Building" list, inline quote, "The Lesson", next-page link). Verified live: 200 OK. | E70: Phase 4 — Marketing Core Pages (30 routes)
B71: /the-body | C71: Done | D71: TheBody.tsx. Real content ported (Alt Therapy Scorecard, Current Protocols, Peptide Research Tools links, pull quote, "The Lesson"). Hero image rescued from legacy /api/img/ into Sanity before porting. Verified live: 200 OK, real image. | E71: Phase 4 — Marketing Core Pages (30 routes)
B72: /the-nightstand | C72: Done | D72: Nightstand.tsx. Real content ported (7 books, 5 key concepts, pull quote, "The Lesson"). Hero image rescued into Sanity. Verified live: 200 OK, real image. | E72: Phase 4 — Marketing Core Pages (30 routes)
B73: /the-web | C73: Done | D73: TheWeb.tsx. Real content ported (20 client badges, 4 key partnerships, pull quote, adage strip, "The Lesson"). Hero image rescued into Sanity. Verified live: 200 OK, real image. | E73: Phase 4 — Marketing Core Pages (30 routes)
B74: /pick-up-the-phone | C74: Done | D74: PickUp.tsx. Real content ported (Engagement Audit CTA to /engage, email/location, "What to Talk About" topics, social links, pull quote, "The Lesson"). Verified live: 200 OK. | E74: Phase 4 — Marketing Core Pages (30 routes)
B75: /journeys | C75: Done | D75: Journeys.tsx. Real content ported (7 curated journeys, all real stops/teasers), rebuilt as a proper shadcn Accordion instead of hand-rolled expand state. Fixed 2 legacy bugs: stops pointing at / meant the old homepage — remapped to /the-letter since / is now the blog index; 3 "Crusade Files" stops pointed at the generic /blog placeholder instead of the specific post — corrected to real slugs. Also caught a real SEO issue: shadcn's AccordionContent doesn't render collapsed-panel children into the DOM at all by default — every internal link on this link-heavy page was invisible to crawlers until a user clicked to expand it. Fixed with forceMount (documented inline). Worth checking any other page that ends up using Accordion for real content, not just decoration. Verified live: 200 OK, all links (including the corrected ones) present in the raw server-rendered HTML, not just after hydration. | E75: Phase 4 — Marketing Core Pages (30 routes)
B76: /recent-creations | C76: Done | D76: Portfolio.tsx. Real content ported (11 project cards, real accent colors — the one legitimate per-item inline-style exception, static Tailwind classes can't express 11 runtime hex values). Fixed a dead internal link (Homeaglow Exposed pointed at a route that doesn't exist anywhere; corrected to the real external homeaglowexposed.com already used consistently on other ported pages) and remapped / → /the-letter. Flagged but did NOT fix: "FusionRamp / STRATUM" points at /humanos, same as the unrelated Human OS card — looks like a copy-paste bug but there's no confirmed correct destination anywhere in the codebase, so ported as-is with a comment rather than guessed; worth a content-team check. Verified live: 200 OK, fixed links present. | E76: Phase 4 — Marketing Core Pages (30 routes)
... B128: /america-unbundled | C128: Done | D128: live-only Part One, "AI Does Not Have a Candidate" (no legacy file). Ported 2026-10-01 from the live page: copy, links, title/description/keywords/OG and Article JSON-LD verbatim; same series masthead and styling as Part Two; hero is the same rescued Sanity image (age-of-ai-no-party). The "Share the question" rail is a tiny client island (components/america-unbundled/share-rail.tsx: copy link + device share; X/LinkedIn are plain links). #sources anchor kept for Part Two's link. Temporary /america-unbundled → / redirect removed from next.config.ts. | E128: Phase 4 — Marketing Core Pages (30 routes)
A129: Phase 5 — Blog Engine (Sanity-backed)
B130: / and /blog | C130: Done | D130: blog index, paginated (12/page), category filter pills, real Sanity data — verified live: 200 OK, real post links, real category links | E130: Phase 5 — Blog Engine (Sanity-backed)
B131: /blog/[slug] | C131: Done | D131: post template: hero image (next/image), portable text renderer, byline/reading time, pull quote (added pullQuote field to the post schema + backfilled 15 posts that had one — wasn't in the original schema, would've been silently dropped otherwise), drop caps (CSS ::first-letter on the article's first paragraph, in globals.css — position-based, not per-post data, so it works for every post automatically), related posts (same-category, falling back to most-recent) — verified live against a real post: correct <title>, correct read time, body rendered | E131: Phase 5 — Blog Engine (Sanity-backed)
B132: /blog/category/[slug] | C132: Done | D132: category listing + pagination (not explicitly in the original phase list, but linked from the index's category pills — built so that link isn't a 404; own quality bar already requires "every page links to 2+", not dead links) | E132: Phase 5 — Blog Engine (Sanity-backed)
B133: generateStaticParams for all post slugs and category slugs (SSG) | C133: Done | E133: Phase 5 — Blog Engine (Sanity-backed)
B134: sitemap.ts already live from real Sanity data (122 URLs verified | C134: Done | D134: homepage + 121 posts) | E134: Phase 5 — Blog Engine (Sanity-backed)
B135: /search | C135: Done | D135: full-text search across posts (built, not yet pushed — pending local review). No legacy Search.tsx ever existed — this is a genuinely new page, not a port (Phase 5's plan noted the GROQ query searchPostsQuery was already written but the page wasn't). Built as a pure Server Component: a plain GET <form> to /search?q=... needs no client JS at all, sanityFetch(searchPostsQuery, ...) runs server-side per this repo's data-fetching rule, results render with the existing PostCard. Was an orphan page (only reachable via /series' already-corrected link) — added a search icon to site-header.tsx (desktop + mobile) linking to /search so it has a real, discoverable entry point. Verified live: 200 OK empty state, ?q=trust returns 30 real matched posts (capped by the query's own [0...30]), typecheck/lint/production-build clean. | E135: Phase 5 — Blog Engine (Sanity-backed)
B136: Header search icon → command-palette modal, matching legacy's real SearchPalette.tsx UX (a page-navigation link before this) | C136: Done | D136: Ported the real ~121-entry PAGES directory (data/searchablePages.ts is a grep-confirmed-dead older duplicate, not used) into lib/content/search-directory.ts, and the real word-frequency/multi-word-AND relevance scoring from lib/searchEngine.ts into lib/search-engine.ts. Fixed 3 stale /assessments/* hrefs to their real canonical routes, repointed the dead /the-index link to /search, and repointed 5 pre-consolidation Attention Theft sub-page links to real in-page anchors on the consolidated /attention-theft. Dropped 4 entries with no real route and no documented deferral (FauxTony, The Open Door, Alex Azzi, Spamtoast — Alex Azzi has since been ported, see below; should be re-added to the directory in a follow-up). Built components/search-modal.tsx on the existing shadcn Dialog (no cmdk, no framer-motion, no new dependency) with a real global Cmd/Ctrl+K shortcut, arrow-key nav + Enter-to-open, and Escape/backdrop close (free from Radix). Blog-post search is a debounced (250ms) fetch to a new app/api/search/route.ts, reusing /search's existing searchPostsQuery/sanityFetch rather than adding a new GROQ query, re-ranked server-side with the same relevance scorer used for static pages — legacy's TF-IDF body-density scoring wasn't portable since Sanity content isn't bundled client-side the way legacy's blogData.json was. Real Loader2 spinner during the fetch, no "..." text. Replaced both header <Link href="/search"> search icons (desktop + mobile) with buttons that open the modal; /s | E136: Phase 5 — Blog Engine (Sanity-backed)
B137: /articles | C137: Done | D137: full archive grouped by category (built, not yet pushed — pending local review). Real content ported in full — all 6 discovery-mode curations (Start Here, Short Reads, Deep Dives, Contrarian, Changed His Mind, Surprise Me) with their real curated slug lists, all 8 real category descriptions, category-grouped default view, search. Built ArticlesExplorer (client, components/blog/articles-explorer.tsx) + lib/content/articles-discovery.ts. Posts now come live from Sanity (allPostsForArchiveQuery) instead of the static blogData.json import. Caught and fixed a real legacy bug: 3 of the curated discovery-mode slugs (psychedelics-could-become-extractive-capitalism-unless, enterprise-blockchain-can-big-business-co-opt-an-existing-technology, an-ode-to-kusaki-where-plants-become-culinary-art) didn't match any real post slug — verified against blogData.json, corrected to the real slugs, same class of stale-slug bug already fixed on /journeys//recent-creations//series. Footer "SUBSCRIBE" CTA linked to /subscribe (Stripe-backed, deferred) — replaced with a link to /blog. Verified live: 200 OK, all discovery modes + categories present, both corrected slugs render as real working links, typecheck/lint/production-build clean. | E137: Phase 5 — Blog Engine (Sanity-backed)
B138: /thesis-threads | C138: Done | D138: curated-by-thread view (built, not yet pushed — pending local review). No legacy port of a data file was needed — lib/content/thesis-threads.ts (Tony's own newsletter-curation "content DNA" document, ported from legacy client/src/data/sitePrompt.ts) already existed from an earlier pass with all 69 articleSlugs pre-verified against the real post corpus. Built ThesisThreadsExplorer (client, components/blog/thesis-threads-explorer.tsx) + app/thesis-threads/page.tsx (Server Component, sanityFetch(allPostsForArchiveQuery)). 4 tabs ported in full: Thesis Threads (6 threads, thread selector, per-thread article list with real THESIS_CONNECTORS pull-quotes, unmapped-articles section), Section Map (5 section-to-thesis cards), Research Library (6 citations + 4 LP comparables), Content Rules (voice, 6 content rules, "never use" word list). Fixed legacy's /read/[slug] links to this site's real /blog/[slug] pattern. Two decorative simplifications, matching calls already made elsewhere in this migration: canvas-based floating particles dropped (same as home-hero.tsx), and the legacy hero's generic Unsplash stock photo + scroll-parallax dropped for a plain dark band (not a real editorial image worth rescuing into Sanity, same call as the peptide pages' dead CloudFront heroes). Was an orphan page — added to site-nav-data.ts's "Read" mega-menu category, next to "All Essays". Verified live: 200 OK, stats strip shows real counts (121 essays, 69 mapped, 52 unmapped — matches the data module's own | E138: Phase 5 — Blog Engine (Sanity-backed)
B139: /impact-futurism | C139: Done | D139: curated category view (built, not yet pushed — pending local review). Real content ported in full — all 7 real essays (3 featured + 4 more) across 5 tags (Health Systems, AI & Energy, Psychedelic Medicine, Infrastructure, Trust & Verification), curated teaser copy, tag filter. Built ImpactFuturismExplorer (client, components/blog/impact-futurism-explorer.tsx) + lib/content/impact-futurism.ts (curated tag/teaser only — real title/date/hero-image/read-time now come live from Sanity via allPostsForArchiveQuery, same content-boundary split as articles-discovery.ts/thesis-threads.ts). Legacy's per-article hero images (/manus-storage/... — banned Manus host — plus one dead CloudFront URL) dropped in favor of each real post's own Sanity heroImage, already present per post, no rescue needed. Both "Get the Dispatch" CTAs linked to /subscribe (Stripe-backed, deferred) — replaced with /blog, same fix already applied on /articles. Fixed legacy's stale hardcoded "All 121 Essays" to a live posts.length. Was an orphan page — added to site-nav-data.ts's "Read" mega-menu category. Verified live: 200 OK, all 7 real titles + real Sanity hero images render, live essay count (121) confirmed in SSR HTML, typecheck/lint clean. | E139: Phase 5 — Blog Engine (Sanity-backed)
B140: On-demand webhook-triggered revalidation on Sanity publish (built, not yet pushed | C140: Done | D140: pending local review). Corrected mislabel: the old note here said "Phase 11", but Phase 11 is the unrelated Publish-Approval Workflow (Supabase dashboard) — this is its own small piece of infra, not part of that phase. Built app/api/revalidate/route.ts: a Route Handler using next-sanity/webhook's parseBody (wraps @sanity/webhook's isValidSignature — already a transitive dep via next-sanity, no new package needed) to verify the request against SANITY_WEBHOOK_SECRET (already reserved in .env.local.example from an earlier pass, never actually wired up). On a valid signature, calls revalidateTag("sanity", { expire: 0 }) — every sanityFetch() call already tags its cache entry "sanity" (see lib/sanity/client.ts), so one tag covers every Sanity-backed page, no per-route path list to maintain. Real Next.js 16 breaking change caught: revalidateTag(tag) (single-argument) is deprecated and now a type error — the second argument is required. Read node_modules/next/dist/docs/.../revalidateTag.md rather than assuming the old signature; its own webhook example calls out { expire: 0 } specifically for "webhooks or third-party services that need immediate expiration" (the default recommended profile: "max" only refreshes on next visit, wrong for this case). Still needs a human step this migration can't do: creating the actual webhook in Sanity's project dashboard (manage.sanity.io → API → Webhooks) pointing at /api/revalidate with a matching secret — documented in the route's own file comment | E140: Phase 5 — Blog Engine (Sanity-backed)
B141: Article footer standardization (built, not yet pushed | C141: Done | D141: pending local review). Real content ported for all 121 entries from footerData.json (exercise / 2-4 curated related links with hand-written reasons / riddle / further reading), keyed by slug. Built ArticleFooter (components/blog/article-footer.tsx) + lib/content/article-footers.ts, wired into app/blog/[slug]/page.tsx after the "Read next" section. Fetched all 121 real post slugs from Sanity to cross-check every related[].slug reference — found and fixed 3 real stale slugs across 2 renamed posts (the Bentley/EV piece and the Butcher's Daughter piece each had a different stale slug pointing at them), same class of bug already fixed on /journeys//articles//series. Also found: (1) one entry used a relatedArticles key instead of related — the key BlogPost.tsx actually reads — meaning that post's related-links block silently never rendered even in legacy; normalized to related. (2) a trueSelfCTA field in one entry that BlogPost.tsx never reads at all (grepped — zero usages) — dead data, dropped rather than ported. (3) an exercise.steps checklist in one entry that legacy authored but never rendered (component only reads exercise.title/.description) — real content, so rendered here instead of repeating the oversight. The one slug: "manifesto" sentinel (legacy's in-code special case for "link to the manifesto, not a post") resolved to a real href: "/living-declaration" in the data itself. The hardcoded "TrueSelf Soul Print Assessment" CTA (identical on every legacy post) is kept, but | E141: Phase 5 — Blog Engine (Sanity-backed)
B142: Spot-check all 121 migrated posts' body formatting (automated, not a Studio visual pass | C142: Done | D142: see note below on what that still leaves open). Wrote a one-off script fetching every post's body from Sanity and scanning for markdown-conversion artifacts (unconverted bold/text/headings/bullets, leaked HTML tags, empty text blocks, link marks with no href). Flagged 12 of 121. Two real bugs found and one fixed: (1) ~8 posts have link marks with href: "" — traced to the actual root cause by reading blogData.json's raw originalContent markdown directly: the source markdown itself has text links with an already-empty URL (predates this migration entirely — e.g. the-tug-of-war-ethical-vs-economic-decisions has subsidy, dairy kills, etc., empty parens in the original text). portable-text.tsx's link renderer was defaulting a missing href to "#", silently turning lost-forever data into a fake dead link on every affected post. Fixed at the renderer level (real code, not data): a link mark with no href now renders its text plain, with no anchor wrapper — verified live on the-tug-of-war-ethical-vs-economic-decisions (zero href="#" in the rendered HTML, previously-"linked" words like "subsidy" and "dairy kills" still read fine as plain text). (2) 4 posts (energy-is-money-money-is-memory, frqncy-the-bus-that-restores-the-world, is-that-a-lot-clarisse-abelarde, you-are-the-moat) had literal un-rendered !alt markdown image syntax visible as plain paragraph text — the markdown→Portable-Text converter (scripts/markdown-to-portable-text.ts) never had image-syntax handling at all. Checked al | E142: Phase 5 — Blog Engine (Sanity-backed)
B143: Reconcile blogData.json vs. the legacy blogPosts.ts module. Resolved | C143: Done | D143: not a duplicate. Traced blogPosts.ts's own header comment ("Blog Post Data — 20 most recent posts... original excerpt, AI-rewritten 'Updated for Today' version") plus its actual 25-entry BlogPost[] array: this is a distinct, unrelated, much smaller dataset (an AI-rewrite/"TonyG Format" exercise with lesson/nextSteps fields) that was never the input to migrate-blog-posts.ts, which reads only blogData.json (confirmed in that script's own top-of-file comment and its LegacyPost type). blogData.json is the sole authoritative source for the 121-post corpus; blogPosts.ts was never a candidate alternate and needs no reconciliation — it's simply out of scope, superseded implicitly by the real 121-post migration. | E143: Phase 5 — Blog Engine (Sanity-backed)
B144: Preserve internal cross-link structure from client/src/data/linkMap.ts / readingPaths.ts (built, not yet pushed | C144: Done | D144: pending local review). Both ported as real, working features, not just cross-referenced. | E144: Phase 5 — Blog Engine (Sanity-backed)
B145: Post extras from live (2026-10-01) | C145: Done | D145: every post now shows the blocks legacy BlogPost.tsx and live render around the essay: format tag, validity score and series badge in the header, the summary, "Before You Read" (Reveal/Hint via <details>, answer in the server HTML), then The Lesson, Next Steps, Further Reading, Voices in This Space / Also involves, Since this was written, and the series reading list. Data ported unchanged into src/lib/content/post-extras.ts (from blogData.json, riddleData.ts, thoughtLeaders.ts), further-reading.ts and essay-series.ts (now shared with /series); component src/components/blog/post-extras.tsx. Checked against live: lesson, next steps and validity match on every post that loaded. Left out on purpose: read counts, reactions/comments/"Rate this thinking" (no backend), and the "Updated for Today" toggle (an AI rewrite; live defaults to the original text, which is what Sanity holds). | E145: Phase 5 — Blog Engine (Sanity-backed)
... B157: Essay archive: search suggestions + more filters | C157: Done | D157: (owner asked 2026-10-14, chose: search-as-you-type, and sort, year, reading time, topic). The archive at the bottom of / (and on /blog) was already live data (Sanity, newest first, refreshed within 60s or by the webhook; every essay on live's sitemap is in Sanity). Added: archive-search-box.tsx, a dropdown while typing with matching categories and topics (instant) and essays from /api/search (also matches words inside the essay text); arrow keys + Enter, Escape. Filters: Newest/Oldest, Year, Reading time (under 5, 5 to 10, over 10 min) and Topic (tags used by 3+ essays, about 30 of 874), with "Clear filters"; on phones they fold behind a "Filters" button. Reading time uses the editor's value or a word-count estimate (minutes in allPostsForArchiveQuery; only 34 of 123 posts had one). Checked: type check, lint, build (150 static / 28 dynamic, unchanged), browser on a fresh server: every filter count matches the data (year 2010: 21, neuroscience: 13, 5 to 10 min: 52...), "kurzweil" suggests the H+ essays and Enter opens one, picking a topic suggestion sets the Topic filter; 375 light/dark, 820, 1280: no sideways scroll, no JS errors. | E157: Phase 5 — Blog Engine (Sanity-backed)
A158: Phase 6 — BrewSoul (28 routes)
B159: /brewsoul | C159: Done | D159: welcome/landing gate (built, not yet pushed — pending local review), along with the shared foundation the rest of Phase 6 depends on. Ported BrewSoulLayout.tsx → app/brewsoul/layout.tsx + components/brewsoul/brewsoul-nav.tsx (BrewSoulNav/BrewSoulFooter), CategoryBadge.tsx → components/brewsoul/category-badge.tsx, brewsoul-config.ts → lib/content/brewsoul-config.ts, and BrewSoulDirectory.tsx's CATEGORIES/PAGE_CATEGORY_MAP data (not the page itself yet) → lib/content/brewsoul-directory.ts. Real architecture decision: BrewSoul is a self-contained sub-site with its own nav/footer/coffee-brown palette, same as legacy — but this app has one flat root layout with no route groups, so the main site's SiteHeader/SiteFooter needed to be suppressed for this one subtree without restructuring every existing route. Added components/site-chrome.tsx (SiteChrome, a small client wrapper checking pathname.startsWith("/brewsoul")) around both in app/layout.tsx — verified via literal <header>/<footer>/<nav> tag counts in real SSR HTML (not text search, which false-positives on Next dev mode's RSC debug payload) that /brewsoul gets zero main-site chrome and its own real nav+footer, while / still gets exactly one of each. Dropped TonyAvatarTrigger (FauxTony chatbot widget — Phase 10, no backend yet, same "don't fake it" call made elsewhere) from the nav. Ported BrewSoulWelcome.tsx → components/brewsoul/brewsoul-welcome-quiz.tsx (8-screen onboarding quiz, real identity-scoring logic, palate questions | E159: Phase 6 — BrewSoul (28 routes)
B160: /brewsoul/first-sip | C160: Done | D160: onboarding intro (built, not yet pushed — pending local review). Ported "The First Sip Is a Vote" in full — the complete manifesto essay (5 sections, 3 pullquotes, the couplets block, the disclosure-demands grid), the 5-tool journey map, 6 related-essay links (real slugs, cross-checked against this session's already-verified corpus), the closing + sources, and the email capture. Built as a Server Component (all static except the email form) + components/brewsoul/next-steps.tsx (shared "what's next" CTA, itself a Server Component — legacy's hover effects were plain CSS-able, no JS state needed) + components/brewsoul/first-sip-email-capture.tsx (client island, mailto: fallback since no subscribe backend exists, same pattern as newsletter-popup.tsx). Dropped the canvas CoffeeDust decoration and the confirmed-dead hero photo (/api/img/brewsoul-orig_84eb4bc9.jpg, 404, same Manus proxy) — with no image left, the scroll-linked parallax that moved it went too. The 5 tool-card links (prescription/health/pairings/economics/compare) point at later Phase 6 routes not built yet — same forward-reference pattern as /find-my. Verified live: 200 OK, full essay text present, CategoryBadge correctly shows "Start Here" (from PAGE_CATEGORY_MAP), zero main-site chrome leaking in, typecheck/lint clean. | E160: Phase 6 — BrewSoul (28 routes)
B161: /brewsoul/home | C161: Done | D161: the real BrewSoul dashboard (distinct from /brewsoul's identity-quiz welcome gate and /brewsoul/first-sip's manifesto): hero + stats, Follow the Dollar teaser, Top QPR coffees (computed live via computeQPR), the 2025 crisis callout, New Drops, a Wall of Shame preview (SHAME_ENTRIES), the research-hub card grid, and a cyclable health-fact ticker (components/brewsoul/health-ticker.tsx, its own small client island so the rest of the page stays a Server Component). Canvas WarmParticles/ParallaxBg decorations and the dead hero photo (/api/img/brewsoul-orig_84eb4bc9.jpg, same confirmed-404 Manus proxy used elsewhere in Phase 6) dropped for CSS gradients. Stats use the real live BREWSOUL_COFFEES.length (107) in place of legacy's stale "103". Verified live: 200 OK. | E161: Phase 6 — BrewSoul (28 routes)
B162: /brewsoul/browse | C162: Done | D162: coffee listing (components/brewsoul/browse-explorer.tsx), real filter/search over the full BREWSOUL_COFFEES catalog. Verified live: 200 OK. | E162: Phase 6 — BrewSoul (28 routes)
B163: /brewsoul/coffee/[id] | C163: Done | D163: coffee detail page (breadcrumb, QPR + tier header, quick stats, tasting notes, flavor-profile bars, the 4 intelligence scores, transparency/ethics data, buy links, competition wins, similar-coffees cross-links, journey CTAs), server-rendered with generateStaticParams over all 107 real coffees (this repo's bounded-dynamic-route convention, same as /blog/[slug]) instead of legacy's client-side useParams lookup. Verified live: 200 OK. | E163: Phase 6 — BrewSoul (28 routes)
...

Sheet Remaining Work
A1: Phase | B1: Route / Item | C1: Status | D1: Why it's not done / what's blocking it | E1: Phase name
A2: Phase 4 — Marketing Core Pages (30 routes)
B3: /shop, /payment-success, /payment-cancel | C3: Deferred | D3: defer: (2026-10-13: /shop temporarily redirects to /subscribe; delete that entry in SEARCH_CONSOLE_TEMPORARY_REDIRECTS when this is built) these are Stripe-backed; flag for the later billing-migration phase, do not port checkout logic yet, static/informational content only if ported now | E3: Phase 4 — Marketing Core Pages (30 routes)
A4: Phase 11 — Code MCP Server — REBUILT (2026-09-29)
B5: Set GITHUB_TOKEN, MCP_ADMIN_USERS, MCP_LOGIN_PASSWORD, MCP_OAUTH_SECRET, MCP_SITE_ORIGIN, MCP_PUBLIC_ORIGIN in Netlify (done) (checked 2026-… | C5: Remaining | D5: 10-07: all already set in Netlify). Left: connect Claude.ai to /api/mcp for real, and verify the GitHub flow end to end (branch → PR → deploy preview → publish_changes) against a real PR. | E5: Phase 11 — Code MCP Server — REBUILT (2026-09-29)
B6: Commit a team-wide .mcp.json (URL only) once the production URL is settled. | C6: Remaining | E6: Phase 11 — Code MCP Server — REBUILT (2026-09-29)
B7: Test the new review end to end on a deploy preview | C7: Remaining | D7: (needs a yes, it opens a real pull request): one throwaway change from Claude.ai or ChatGPT: start (unclear request, so the confirm step shows), confirm, edit, review card, screenshots, upload link, then discard. | E7: Phase 11 — Code MCP Server — REBUILT (2026-09-29)
A8: Phase 12 — SEO Hardening, Redirects & Cutover Prep
B9: Connect Google Search Console + GA4 to the new deployment on day one of cutover | C9: Remaining | E9: Phase 12 — SEO Hardening, Redirects & Cutover Prep
A10: Phase 14 — QA & Launch
B11: Find Your Me: pick real essays for two results (2026-10-16), needs Tony | C11: Remaining | D11: The Systems | E11: Phase 14 — QA & Launch
B12: Quiz content questions for Tony (2026-10-16) | C12: Remaining | D12: Consciousness Scale: the answer scores only | E12: Phase 14 — QA & Launch
B13: DNS cutover, legacy app decommissioned only after a stable overlap window Re-checked 2026-10-13 | C13: Remaining | D13: unchanged (Hostinger name servers, bare domain on Manus 104.19.168/169.112, www CNAME cname.manus.space). Checked 2026-10-09 (owner wants to go live and switch off Manus): DNS for tonygreenberg.com is at Hostinger (name servers ns1/ns2.dns-parking.com); www is a CNAME to cname.manus.space, the bare domain points at Manus's addresses (104.19.168.112 / .169.112); the Netlify site tonygreenberg-website has no custom domain yet (production branch main). Order: (1) merge the three open pull requests into main and check the Netlify copy; (2) restore Supabase and run 0001 to 0003, or launch without member features (they say "isn't available just now"); (3) owner sign-off; (4) add tonygreenberg.com + www in Netlify (Domain management), then at Hostinger point the bare domain at Netlify (A record 75.2.60.5, or Netlify DNS) and www CNAME at tonygreenberg-website.netlify.app; Netlify issues the HTTPS certificate; (5) re-run scripts/check-search-console-urls.ts https://tonygreenberg.com and submit the sitemap in Search Console; (6) only after a few stable days: switch off the Manus site (the database is already backed up, docs/ai/project_legacy_database.md) and rotate the old database password. | E13: Phase 14 — QA & Launch
